redis_lock/__init__.py
redis_lock/base.py
redis_lock/exceptions.py
redis_lock/lock.py
redis_lock/spin_lock.py
redis_lock/types.py
redis_lock/asyncio/__init__.py
redis_lock/asyncio/async_lock.py
redis_lock/asyncio/base.py
redis_lock_py-1.2.1.dist-info/METADATA
redis_lock_py-1.2.1.dist-info/WHEEL
redis_lock_py-1.2.1.dist-info/licenses/LICENSE
redis_lock_py-1.2.1.dist-info/RECORD
