Metadata-Version: 2.4
Name: redis-lock-py
Version: 1.2.1
Summary: Redis distributed lock implementation for Python based on Pub/Sub messaging
Project-URL: Homepage, https://github.com/miintto/redis-lock-py
Author-email: Minjae Park <miintto.log@gmail.com>
License-Expression: MIT
License-File: LICENSE
Classifier: Development Status :: 5 - Production/Stable
Classifier: License :: OSI Approved :: MIT License
Classifier: Programming Language :: Python :: 3
Classifier: Programming Language :: Python :: 3.10
Classifier: Programming Language :: Python :: 3.11
Classifier: Programming Language :: Python :: 3.12
Classifier: Programming Language :: Python :: 3.13
Classifier: Programming Language :: Python :: 3.14
Requires-Python: >=3.10
Requires-Dist: redis>=7.0.1
Provides-Extra: test
Requires-Dist: coverage>=7.11.3; extra == 'test'
Requires-Dist: pytest-asyncio>=1.3.0; extra == 'test'
Requires-Dist: pytest>=9.0.1; extra == 'test'
